waapuro/__init__.py
waapuro/test/__init__.py
waapuro/test/test_waapuro.py
waapuro-1.0.1.dist-info/DESCRIPTION.rst
waapuro-1.0.1.dist-info/METADATA
waapuro-1.0.1.dist-info/metadata.json
waapuro-1.0.1.dist-info/RECORD
waapuro-1.0.1.dist-info/top_level.txt
waapuro-1.0.1.dist-info/WHEEL
