Metadata-Version: 2.0
Name: waapuro
Version: 1.0.1
Summary: A dead-simple hiragana and katakana romanization library
Home-page: https://github.com/kxz/waapuro
Author: Kevin Xiwei Zheng
Author-email: blankplacement+waapuro@gmail.com
License: X11
Keywords: japanese kana hiragana katakana romanization
Platform: UNKNOWN
Classifier: Development Status :: 3 - Alpha
Classifier: Intended Audience :: Developers
Classifier: License :: OSI Approved :: MIT License
Classifier: Natural Language :: Japanese
Classifier: Operating System :: OS Independent
Classifier: Programming Language :: Python :: 2
Classifier: Programming Language :: Python :: 2.7
Classifier: Programming Language :: Python :: 3
Classifier: Programming Language :: Python :: 3.4
Classifier: Topic :: Software Development :: Libraries
Requires-Dist: future
